smart_2fa_secure/__init__.py
smart_2fa_secure/core.py
smart_2fa_secure/exceptions.py
smart_2fa_secure/generators.py
smart_2fa_secure/interfaces.py
smart_2fa_secure/backends/__init__.py
smart_2fa_secure/backends/redis.py
smart_2fa_secure/backends/telegram.py
smart_2fa_secure-0.2.3.dist-info/licenses/LICENSE
tests/__init__.py
tests/conftest.py
tests/unit/__init__.py
tests/unit/test_core.py
tests/unit/test_exceptions.py
tests/unit/integrations/__init__.py
tests/unit/integrations/test_integrations.py
tests/unit/test_backends/__init__.py
tests/unit/test_backends/test_redis.py
tests/unit/test_backends/test_telegram.py
smart_2fa_secure-0.2.3.dist-info/METADATA
smart_2fa_secure-0.2.3.dist-info/WHEEL
smart_2fa_secure-0.2.3.dist-info/top_level.txt
smart_2fa_secure-0.2.3.dist-info/RECORD
