Metadata-Version: 2.4
Name: smart-2fa-secure
Version: 0.2.3
Summary: Advanced Two-Factor Authentication system with enhanced security features.
Author-email: "A.A. Suvorov" <smartlegiondev@gmail.com>
License-Expression: BSD-3-Clause
Project-URL: Homepage, https://github.com/smartlegionlab/smart-2fa-secure
Project-URL: Documentation, https://github.com/smartlegionlab/smart-2fa-secure#readme
Classifier: Programming Language :: Python :: 3
Classifier: Operating System :: OS Independent
Requires-Python: >=3.8
License-File: LICENSE
Requires-Dist: redis~=6.2.0
Requires-Dist: requests~=2.32.4
Dynamic: license-file
